<?xml version="1.0" encoding="utf-8"?>
<!DOCTYPE hibernate-mapping PUBLIC "-//Hibernate/Hibernate Mapping DTD 3.0//EN"
"http://hibernate.sourceforge.net/hibernate-mapping-3.0.dtd">
<!-- 
    Mapping file autogenerated by MyEclipse Persistence Tools
-->
<hibernate-mapping>
    <class name="com.zqdy.dao.po.TTvArea" table="t_tv_area" >
        <id name="id" type="java.lang.Integer">
            <column name="id" />
            <generator class="identity" />
        </id>
         
        <many-to-one name="area" column="area_id"></many-to-one>
        <property name="tvId" type="java.lang.Integer">
            <column name="tv_id" not-null="true">
                <comment>电视剧ID</comment>
            </column>
        </property>
    </class>
</hibernate-mapping>
